README.rst
setup.py
xfail.py
xfail.egg-info/PKG-INFO
xfail.egg-info/SOURCES.txt
xfail.egg-info/dependency_links.txt
xfail.egg-info/not-zip-safe
xfail.egg-info/top_level.txt