Metadata-Version: 1.1
Name: xfail
Version: 1.1.0
Summary: Skip expected failures and raise error if unexpectedly passed
Home-page: https://github.com/miyakogi/xfail.py
Author: Hiroyuki Takagi
Author-email: miyako.dev@gmail.com
License: MIT
Keywords: xfail
Platform: UNKNOWN
Classifier: Development Status :: 5 - Production/Stable
Classifier: Intended Audience :: Developers
Classifier: License :: OSI Approved :: MIT License
Classifier: Natural Language :: English
Classifier: Programming Language :: Python :: 2
Classifier: Programming Language :: Python :: 2.7
Classifier: Programming Language :: Python :: 3
Classifier: Programming Language :: Python :: 3.4
Classifier: Programming Language :: Python :: 3.5
